LICENSE
MANIFEST.in
README.rst
requirements.txt
setup.py
beamspy/__init__.py
beamspy/__main__.py
beamspy/annotation.py
beamspy/auxiliary.py
beamspy/db_parsers.py
beamspy/grouping.py
beamspy/gui.py
beamspy/in_out.py
beamspy/libraries.py
beamspy/plots.py
beamspy/statistics.py
beamspy.egg-info/PKG-INFO
beamspy.egg-info/SOURCES.txt
beamspy.egg-info/dependency_links.txt
beamspy.egg-info/entry_points.txt
beamspy.egg-info/requires.txt
beamspy.egg-info/top_level.txt
beamspy/data/adducts.txt
beamspy/data/db_compounds.txt
beamspy/data/db_mf.txt
beamspy/data/isotopes.txt
beamspy/data/multiple_charged_ions.txt
beamspy/data/neutral_losses.txt
beamspy/data/nist_database.txt
beamspy/data/databases/biocyc_chlamycyc_20180702_v1.sql.gz
beamspy/data/databases/chebi_complete_3star_rel195_v1.sql.gz
beamspy/data/databases/chebi_complete_rel195_v1.sql.gz
beamspy/data/databases/databases.txt
beamspy/data/databases/hmdb_csf_v4_0_20200910_v1.sql.gz
beamspy/data/databases/hmdb_feces_v4_0_20200910_v1.sql.gz
beamspy/data/databases/hmdb_full_v4_0_20200909_v1.sql.gz
beamspy/data/databases/hmdb_saliva_v4_0_20200910_v1.sql.gz
beamspy/data/databases/hmdb_serum_v4_0_20200910_v1.sql.gz
beamspy/data/databases/hmdb_sweat_v4_0_20200910_v1.sql.gz
beamspy/data/databases/hmdb_urine_v4_0_20200910_v1.sql.gz
beamspy/data/databases/kegg_dpx_20210111_v1.sql.gz
beamspy/data/databases/kegg_full_20210111_v1.sql.gz
beamspy/data/databases/kegg_hsa_20210111_v1.sql.gz
beamspy/data/databases/lipidmaps_fattyacyls_20201001_v1.sql.gz
beamspy/data/databases/lipidmaps_full_20201001_v1.sql.gz
beamspy/data/databases/lipidmaps_glycerolipids_20201001_v1.sql.gz
beamspy/data/databases/lipidmaps_sacccharolipids_20201001_v1.sql.gz
beamspy/data/databases/lipidmaps_slycerophospholipids_20201001_v1.sql.gz
beamspy/data/databases/lipidmaps_solyketides_20201001_v1.sql.gz
beamspy/data/databases/lipidmaps_sphingolipids_20201001_v1.sql.gz
beamspy/data/databases/lipidmaps_srenollipids_20201001_v1.sql.gz
beamspy/data/databases/lipidmaps_sterollipids_20201001_v1.sql.gz
beamspy/qt/__init__.py
beamspy/qt/form.py
examples/run.py
examples/run.sh
tests/__init__.py
tests/test_annotation.py
tests/test_auxiliary.py
