Metadata-Version: 2.1
Name: beamspy
Version: 1.2.0
Summary: Putative annotation of metabolites for mass spectrometry-based metabolomics datasets.
Home-page: https://github.com/computational-metabolomics/beamspy
Author: Ralf Weber
Author-email: r.j.weber@bham.ac.uk
License: GPLv3
Keywords: Metabolomics,Mass spectrometry,Liquid-Chromatography Mass Spectrometry,Metabolite Annotation
Platform: Windows, UNIX
Classifier: Programming Language :: Python :: 3
Classifier: Programming Language :: Python :: 3.8
Classifier: Programming Language :: Python :: 3.9
Classifier: Programming Language :: Python :: 3.10
Classifier: Topic :: Scientific/Engineering :: Bio-Informatics
Classifier: Topic :: Scientific/Engineering :: Chemistry
Classifier: Topic :: Utilities
Classifier: License :: OSI Approved :: GNU General Public License v3 (GPLv3)
Classifier: Operating System :: OS Independent
Requires-Python: >=3.8
License-File: LICENSE
